dlsia/__init__.py
dlsia/core/__init__.py
dlsia/core/corcoef.py
dlsia/core/custom_losses.py
dlsia/core/helpers.py
dlsia/core/inference_scripts.py
dlsia/core/train_scripts.py
dlsia/core/conformalize/__init__.py
dlsia/core/conformalize/conformalize_segmentation.py
dlsia/core/networks/__init__.py
dlsia/core/networks/aggnet.py
dlsia/core/networks/baggins.py
dlsia/core/networks/cerberus.py
dlsia/core/networks/construct_sms_ensemble.py
dlsia/core/networks/dqr.py
dlsia/core/networks/fcnet.py
dlsia/core/networks/graph_utils.py
dlsia/core/networks/grey2color.py
dlsia/core/networks/msae.py
dlsia/core/networks/msd_graph_tools.py
dlsia/core/networks/msdae.py
dlsia/core/networks/msdnet.py
dlsia/core/networks/msdnet2.py
dlsia/core/networks/orthonet.py
dlsia/core/networks/quantile_regression_networks.py
dlsia/core/networks/random_autoencoder.py
dlsia/core/networks/scale_up_down.py
dlsia/core/networks/sms1d.py
dlsia/core/networks/sms3d.py
dlsia/core/networks/smsnet.py
dlsia/core/networks/sparsenet.py
dlsia/core/networks/squashnet.py
dlsia/core/networks/three_way.py
dlsia/core/networks/tunet.py
dlsia/core/networks/tunet3plus.py
dlsia/core/networks/unet.py
dlsia/core/utils/__init__.py
dlsia/core/utils/agg_utils.py
dlsia/core/utils/blur.py
dlsia/core/utils/downsample.py
dlsia/core/utils/feature_extraction.py
dlsia/core/utils/latent_space_viewer.py
dlsia/core/utils/randomized_data_loader.py
dlsia/core/utils/simple_instance_segmenter.py
dlsia/core/utils/sparse_tools.py
dlsia/test_data/__init__.py
dlsia/test_data/two_d/__init__.py
dlsia/test_data/two_d/build_test_data.py
dlsia/test_data/two_d/diffusion_model.py
dlsia/test_data/two_d/noisy_gauss_2d.py
dlsia/test_data/two_d/noisy_gauss_2d_time.py
dlsia/test_data/two_d/random_shapes.py
dlsia/test_data/two_d/torch_hdf5_loader.py
dlsia/test_data/two_d/tst.py
dlsia/tutorials/__init__.py
dlsia/tutorials/copy_all.py
dlsia/viz_tools/__init__.py
dlsia/viz_tools/draw_sparse_network.py
dlsia/viz_tools/plot_autoencoder_image_classification.py
dlsia-0.3.4.dist-info/licenses/AUTHORS.rst
dlsia-0.3.4.dist-info/licenses/LICENSE
dlsia-0.3.4.dist-info/METADATA
dlsia-0.3.4.dist-info/WHEEL
dlsia-0.3.4.dist-info/top_level.txt
dlsia-0.3.4.dist-info/RECORD
