Metadata-Version: 2.4
Name: dlsia
Version: 0.3.4
Summary: Deep Learning for Scientif Image Analysis
Home-page: https://github.com/phzwart/dlsia/
Author: Petrus H. Zwart, Eric J. Roberts
Author-email: PHZwart@lbl.gov, EJroberts@lbl.gov
License: BSD License
Keywords: dlsia
Classifier: Development Status :: 2 - Pre-Alpha
Classifier: Intended Audience :: Developers
Classifier: License :: OSI Approved :: BSD License
Classifier: Natural Language :: English
Classifier: Programming Language :: Python :: 3.9
Requires-Python: >=3.9
License-File: LICENSE
License-File: AUTHORS.rst
Requires-Dist: setuptools>=62.2.0
Requires-Dist: numpy>=1.23
Requires-Dist: torch>=1.13
Requires-Dist: torchsummary>=1.5.1
Requires-Dist: torchvision>=0.13
Requires-Dist: matplotlib>=3.6.3
Requires-Dist: torchmetrics>=0.4.1
Requires-Dist: tqdm>=4.58.0
Requires-Dist: h5py>=3.1.0
Requires-Dist: plotly>=5.3.1
Requires-Dist: dill>=0.3.4
Requires-Dist: einops>=0.3.0
Requires-Dist: pandas>=1.2.3
Requires-Dist: networkx==3.0
Requires-Dist: scikit-image>=0.18.1
Requires-Dist: scikit-learn>=0.24.1
Requires-Dist: scipy>=1.8.1
Requires-Dist: tifffile>=2021.2.26
Requires-Dist: torchmetrics>=0.11.0
Requires-Dist: qlty>=0.1.7
Requires-Dist: jedi>=0.10
Requires-Dist: connected-components-3d
Requires-Dist: pytorch-lightning
Requires-Dist: sphinx==7.2.6
Requires-Dist: nbsphinx
Requires-Dist: lxml_html_clean
Requires-Dist: nbsphinx-link
Requires-Dist: m2r
Requires-Dist: papermill
Requires-Dist: umap-learn>=0.5.3
Requires-Dist: kaleido
Requires-Dist: zarr
Requires-Dist: sphinx_rtd_theme
Dynamic: author
Dynamic: author-email
Dynamic: classifier
Dynamic: description
Dynamic: description-content-type
Dynamic: home-page
Dynamic: keywords
Dynamic: license
Dynamic: license-file
Dynamic: requires-dist
Dynamic: requires-python
Dynamic: summary
